{
  "mission_data_id":    6,
  "player_unit": [
    { 
      "position":       1,
      "card": [{
        "id":           1103, 
        "level":        3,
        "brnskill":     3021,
        "evolved_cnt":  0
      }],
      "weapon": [{
        "id":           0,
        "level":        0
      }],
      "defender": [{
        "id":           0,
        "level":        0
      }],    
      "shoe": [{
        "id":           0,
        "level":        0
      }],    
      "jewelry": [{
        "id":           0,
        "level":        0
      }],    
      "stdskill1": [{
        "id":           0,
        "level":        0
      }],    
      "stdskill2": [{
        "id":           0,
        "level":        0
      }]
    },
    { 
      "position":       2,
      "card": [{
        "id":           1104, 
        "level":        3,
        "brnskill":     3023,
        "evolved_cnt":  0
      }],
      "weapon": [{
        "id":           0,
        "level":        0
      }],
      "defender": [{
        "id":           0,
        "level":        0
      }],    
      "shoe": [{
        "id":           0,
        "level":        0
      }],    
      "jewelry": [{
        "id":           0,
        "level":        0
      }],    
      "stdskill1": [{
        "id":           0,
        "level":        0
      }],    
      "stdskill2": [{
        "id":           0,
        "level":        0
      }]
    }
  ]
}
